apraw/__init__.py
apraw/const.py
apraw/endpoints.py
apraw/reddit.py
apraw/request_handler.py
apraw/models/__init__.py
apraw/models/user.py
apraw/models/enums/__init__.py
apraw/models/enums/distinguishment_option.py
apraw/models/helpers/__init__.py
apraw/models/helpers/apraw_base.py
apraw/models/helpers/comment_forest.py
apraw/models/helpers/generator.py
apraw/models/helpers/item_moderation.py
apraw/models/helpers/streamable.py
apraw/models/mixins/__init__.py
apraw/models/mixins/author.py
apraw/models/mixins/deletable.py
apraw/models/mixins/hideable.py
apraw/models/mixins/link.py
apraw/models/mixins/nsfwable.py
apraw/models/mixins/redditor.py
apraw/models/mixins/replyable.py
apraw/models/mixins/savable.py
apraw/models/mixins/spoilerable.py
apraw/models/mixins/subreddit.py
apraw/models/mixins/votable.py
apraw/models/reddit/__init__.py
apraw/models/reddit/comment.py
apraw/models/reddit/listing.py
apraw/models/reddit/message.py
apraw/models/reddit/more_comments.py
apraw/models/reddit/redditor.py
apraw/models/reddit/submission.py
apraw/models/subreddit/__init__.py
apraw/models/subreddit/banned.py
apraw/models/subreddit/moderation.py
apraw/models/subreddit/modmail.py
apraw/models/subreddit/removal_reasons.py
apraw/models/subreddit/settings.py
apraw/models/subreddit/subreddit.py
apraw/models/subreddit/wiki.py
apraw/utils/__init__.py
apraw/utils/bounded_set.py
apraw/utils/counter.py
apraw/utils/kind.py
apraw/utils/snake.py
aPRAW-0.6.9a0.dist-info/LICENSE
aPRAW-0.6.9a0.dist-info/METADATA
aPRAW-0.6.9a0.dist-info/WHEEL
aPRAW-0.6.9a0.dist-info/top_level.txt
aPRAW-0.6.9a0.dist-info/RECORD
