Metadata-Version: 2.1
Name: aPRAW
Version: 0.6.9a0
Summary: aPRAW is an asynchronous Reddit API wrapper written in Python.
Home-page: https://github.com/Dan6erbond/aPRAW
Author: Dan6erbond
Author-email: moravrav@gmail.com
License: GNU General Public License v3 (GPLv3)
Keywords: reddit api wrapper async
Platform: UNKNOWN
Classifier: Development Status :: 3 - Alpha
Classifier: Environment :: Console
Classifier: Intended Audience :: Developers
Classifier: License :: OSI Approved :: GNU General Public License v3 (GPLv3)
Classifier: Natural Language :: English
Classifier: Operating System :: OS Independent
Classifier: Programming Language :: Python :: 3.6
Classifier: Programming Language :: Python :: 3.7
Classifier: Programming Language :: Python :: 3.8
Classifier: Topic :: Education
Classifier: Topic :: Internet :: WWW/HTTP :: Dynamic Content :: Message Boards
Classifier: Topic :: Software Development :: Libraries :: Python Modules
Classifier: Topic :: Utilities
Classifier: Typing :: Typed
Requires-Python: >=3.6
